grpc_helper/__init__.py
grpc_helper/cli.py
grpc_helper/client.py
grpc_helper/errors.py
grpc_helper/folders.py
grpc_helper/manager.py
grpc_helper/meta.py
grpc_helper/methods.py
grpc_helper/server.py
grpc_helper/static_config.py
grpc_helper/utils.py
grpc_helper/config/__init__.py
grpc_helper/config/cfg_item.py
grpc_helper/config/cfg_manager.py
grpc_helper/events/__init__.py
grpc_helper/events/events_listener.py
grpc_helper/events/events_manager.py
grpc_helper/logs/__init__.py
grpc_helper/logs/logs_manager.py
grpc_helper/logs/logs_utils.py
grpc_helper-2.3.1.dist-info/LICENSE
grpc_helper-2.3.1.dist-info/METADATA
grpc_helper-2.3.1.dist-info/WHEEL
grpc_helper-2.3.1.dist-info/top_level.txt
grpc_helper-2.3.1.dist-info/RECORD
