Metadata-Version: 2.1
Name: grpc-helper
Version: 2.3.1
Summary: Helpers supercharging grpc features (API versioning, retry, etc...)
Home-page: https://github.com/dynod/grpc-helper
Author: The dynod project
Maintainer: The dynod project
License: Mozilla Public License Version 2.0
Platform: UNKNOWN
Classifier: Programming Language :: Python :: 3.8
Classifier: Programming Language :: Python :: 3.9
Classifier: Programming Language :: Python :: 3.10
Classifier: Programming Language :: Python :: 3.11
Requires-Dist: grpcio
Requires-Dist: protobuf
Requires-Dist: grpc-helper-api
Requires-Dist: argcomplete
